fing_agent_api/__init__.py
fing_agent_api/fing_agent_api.py
fing_agent_api/models/__init__.py
fing_agent_api/models/agent_info_response.py
fing_agent_api/models/contact.py
fing_agent_api/models/contact_info.py
fing_agent_api/models/contact_response.py
fing_agent_api/models/device.py
fing_agent_api/models/device_response.py
fing_agent_api-1.0.3.dist-info/licenses/LICENSE
fing_agent_api-1.0.3.dist-info/METADATA
fing_agent_api-1.0.3.dist-info/WHEEL
fing_agent_api-1.0.3.dist-info/top_level.txt
fing_agent_api-1.0.3.dist-info/RECORD
