Metadata-Version: 2.4
Name: fing_agent_api
Version: 1.0.3
Summary: Fing Agent local API library.
Author-email: Lorenzo Gasparini <lorenzo.gasparini@lansweeper.com>
Project-URL: Homepage, https://github.com/fingltd/fing-agent-pyapi
Project-URL: Issues, https://github.com/fingltd/fing-agent-pyapi/issues
Classifier: Programming Language :: Python :: 3
Classifier: License :: OSI Approved :: Apache Software License
Classifier: Operating System :: OS Independent
Requires-Python: >=3.11.1
License-File: LICENSE
Requires-Dist: httpx
Dynamic: license-file
